jabiru/__init__.py
jabiru/__main__.py
jabiru/version.py
jabiru-0.1.0.dev0.dist-info/LICENSE
jabiru-0.1.0.dev0.dist-info/METADATA
jabiru-0.1.0.dev0.dist-info/WHEEL
jabiru-0.1.0.dev0.dist-info/top_level.txt
jabiru-0.1.0.dev0.dist-info/RECORD
