Metadata-Version: 2.1
Name: jabiru
Version: 0.1.0.dev0
Summary: A javascript language filter for pyspelling
Home-page: https://github.com/resplendent-dev/jabiru
Author: Tim Gates
Author-email: tim.gates@iress.com
Maintainer: Tim Gates
Maintainer-email: tim.gates@iress.com
License: GPLv3+
Platform: UNKNOWN
Classifier: Development Status :: 4 - Beta
Classifier: Programming Language :: Python
Classifier: Programming Language :: Python :: 3
Classifier: Programming Language :: Python :: 3.5
Classifier: Programming Language :: Python :: 3.6
Classifier: Programming Language :: Python :: 3.7
Classifier: Programming Language :: Python :: 3.8
Classifier: Programming Language :: Python :: Implementation :: CPython
Classifier: Programming Language :: Python :: Implementation :: PyPy
Classifier: Operating System :: OS Independent
Classifier: License :: OSI Approved :: GNU General Public License v3 (GPLv3)
Requires-Python: >=3.5
Requires-Dist: pyspelling
